essex_config/__init__.py
essex_config/config.py
essex_config/doc_gen/__init__.py
essex_config/doc_gen/__main__.py
essex_config/doc_gen/doc_gen.py
essex_config/doc_gen/printer/__init__.py
essex_config/doc_gen/printer/markdown_printer.py
essex_config/doc_gen/printer/printer.py
essex_config/doc_gen/printer/rich_printer.py
essex_config/field_annotations.py
essex_config/py.typed
essex_config/sources/__init__.py
essex_config/sources/args_source.py
essex_config/sources/convert_utils.py
essex_config/sources/env_source.py
essex_config/sources/file_source.py
essex_config/sources/keyvault_source.py
essex_config/sources/source.py
essex_config/sources/utils.py
essex_config/utils.py
essex_config-0.0.5.dist-info/METADATA
essex_config-0.0.5.dist-info/WHEEL
essex_config-0.0.5.dist-info/RECORD
