Metadata-Version: 2.1
Name: essex-config
Version: 0.0.5
Summary: Python library for creating configuration objects that read from various sources, including files, environment variables, and Azure Key Vault.
Author: Andres Morales
Author-email: andresmor@microsoft.com
Requires-Python: >=3.10,<4.0
Classifier: Programming Language :: Python :: 3
Classifier: Programming Language :: Python :: 3.10
Classifier: Programming Language :: Python :: 3.11
Classifier: Programming Language :: Python :: 3.12
Requires-Dist: azure-identity (>=1.16.0,<2.0.0)
Requires-Dist: azure-keyvault-secrets (>=4.8.0,<5.0.0)
Requires-Dist: pydantic (>=2.7.3,<3.0.0)
Requires-Dist: python-dotenv (>=1.0.1,<2.0.0)
Requires-Dist: pyyaml (>=6.0.1,<7.0.0)
Requires-Dist: rich (>=13.7.1,<14.0.0)
Requires-Dist: toml (>=0.10.2,<0.11.0)
Requires-Dist: typing-extensions (>=4.12.2,<5.0.0)
Requires-Dist: typing-inspect (>=0.9.0,<0.10.0)
